setup.py
salaryandtaxcalculator/__init__.py
salaryandtaxcalculator/main.py
salaryandtaxcalculator.egg-info/PKG-INFO
salaryandtaxcalculator.egg-info/SOURCES.txt
salaryandtaxcalculator.egg-info/dependency_links.txt
salaryandtaxcalculator.egg-info/top_level.txt