Metadata-Version: 2.1
Name: salaryandtaxcalculator
Version: 1.0.1
Summary: A package that calculates tax based on salary
Author: Pamela Haxhici
Author-email: <pamelahaxhici@gmail.com>
Keywords: salaryandtaxcalculator,SDA,salary,calculator,tax
Classifier: Development Status :: 1 - Planning
Classifier: Intended Audience :: Developers
Classifier: Programming Language :: Python :: 3
Classifier: Operating System :: Unix
Classifier: Operating System :: MacOS :: MacOS X
Classifier: Operating System :: Microsoft :: Windows
